datagovindia/__init__.py
datagovindia/cli.py
datagovindia-1.0.2.dist-info/LICENSE
datagovindia-1.0.2.dist-info/METADATA
datagovindia-1.0.2.dist-info/WHEEL
datagovindia-1.0.2.dist-info/entry_points.txt
datagovindia-1.0.2.dist-info/top_level.txt
datagovindia-1.0.2.dist-info/RECORD
