Metadata-Version: 2.1
Name: datagovindia
Version: 1.0.2
Summary: Python API wrapper for Government of India Open Government Data (OGD) platform data.gov.in
Author: Abhishek Arora
Author-email: Aditya Karan Chhabra <aditya0chhabra@gmail.com>, Arijit Basu <hi@arijitbasu.in>
Maintainer-email: Aditya Karan Chhabra <aditya0chhabra@gmail.com>, Arijit Basu <hi@arijitbasu.in>
License: MIT License
Project-URL: homepage, https://pypi.org/project/datagovindia/
Project-URL: repository, https://github.com/addypy/datagovindia/
Keywords: data.gov.in,indian-government-data,open-data-india,public-datasets,indian-datasets,government-api,india-statistics,ogd-platform
Classifier: License :: OSI Approved :: MIT License
Classifier: Topic :: Database
Classifier: Intended Audience :: Education
Classifier: Intended Audience :: Financial and Insurance Industry
Classifier: Intended Audience :: Information Technology
Classifier: Intended Audience :: Science/Research
Classifier: Programming Language :: Python
Classifier: Programming Language :: Python :: 3
Classifier: Programming Language :: Python :: 3.6
Classifier: Programming Language :: Python :: 3.7
Classifier: Programming Language :: Python :: 3.8
Classifier: Programming Language :: Python :: 3.9
Classifier: Programming Language :: Python :: 3.10
Classifier: Programming Language :: Python :: 3.11
Classifier: Programming Language :: Python :: 3.12
Classifier: Natural Language :: English
Classifier: Operating System :: OS Independent
License-File: LICENSE
Requires-Dist: requests
Requires-Dist: pandas
Requires-Dist: python-dateutil
Requires-Dist: click>=8.0.0
Requires-Dist: tenacity>=6.3.0
